pwdmanager/__init__.py
pwdmanager/commands.py
pwdmanager/database.py
pwdmanager/pwdmanager.py
pwdmanager-1.0.0.dist-info/entry_points.txt
pwdmanager-1.0.0.dist-info/LICENSE
pwdmanager-1.0.0.dist-info/WHEEL
pwdmanager-1.0.0.dist-info/METADATA
pwdmanager-1.0.0.dist-info/RECORD
