Metadata-Version: 2.1
Name: pwdmanager
Version: 1.0.0
Summary: command line tool to manage passwords
Home-page: https://github.com/bravefencermusashi/pwdmanager
License: GPL-3.0
Author: Alexandre G
Author-email: alex.git@ralouf.fr
Requires-Python: >=3.7,<4.0
Classifier: Environment :: Console
Classifier: License :: OSI Approved :: GNU General Public License v3 (GPLv3)
Classifier: Operating System :: OS Independent
Classifier: Programming Language :: Python :: 3
Classifier: Programming Language :: Python :: 3.7
Classifier: Topic :: Security :: Cryptography
Classifier: Topic :: Software Development :: Libraries :: Python Modules
Requires-Dist: python-gnupg (>=0.4.5,<0.5.0)
Project-URL: Repository, https://github.com/bravefencermusashi/pwdmanager
